happybuf/__init__.py
happybuf/capnproto/__init__.py
happybuf/flatbuffers/__init__.py
happybuf/protobuf/__init__.py
happybuf-0.1.0.dist-info/METADATA
happybuf-0.1.0.dist-info/WHEEL
happybuf-0.1.0.dist-info/top_level.txt
happybuf-0.1.0.dist-info/RECORD
