Metadata-Version: 2.1
Name: happybuf
Version: 0.1.0
Summary: UNKNOWN
Home-page: UNKNOWN
License: UNKNOWN
Platform: UNKNOWN
Requires-Dist: flatbuffers
Requires-Dist: protobuf
Requires-Dist: pycapnp
